gitmojis/__init__.py
gitmojis/__main__.py
gitmojis/core.py
gitmojis/defaults.py
gitmojis/exceptions.py
gitmojis/model.py
gitmojis/py.typed
gitmojis/cli/__init__.py
gitmojis/cli/commands.py
python_gitmojis-1.0.0.dist-info/LICENSE
python_gitmojis-1.0.0.dist-info/METADATA
python_gitmojis-1.0.0.dist-info/WHEEL
python_gitmojis-1.0.0.dist-info/entry_points.txt
python_gitmojis-1.0.0.dist-info/top_level.txt
python_gitmojis-1.0.0.dist-info/RECORD
