Metadata-Version: 2.1
Name: python-gitmojis
Version: 1.0.0
Summary: 😜 The official Gitmoji Guide in Python projects 🐍
Author-email: Kamil Paduszyński <paduszyk@gmail.com>
Keywords: emoji,git,gitmoji
Classifier: Development Status :: 5 - Production/Stable
Classifier: Intended Audience :: Developers
Classifier: License :: OSI Approved :: MIT License
Classifier: Operating System :: OS Independent
Classifier: Programming Language :: Python
Classifier: Programming Language :: Python :: 3.10
Classifier: Programming Language :: Python :: 3.11
Classifier: Programming Language :: Python :: 3.12
Classifier: Topic :: Software Development :: Libraries :: Python Modules
Requires-Python: >=3.10
License-File: LICENSE
Requires-Dist: click
Requires-Dist: requests
Provides-Extra: dev
Requires-Dist: nox ; extra == 'dev'
Requires-Dist: pre-commit ; extra == 'dev'
Provides-Extra: lint
Requires-Dist: black ; extra == 'lint'
Requires-Dist: mypy ; extra == 'lint'
Requires-Dist: ruff ; extra == 'lint'
Requires-Dist: types-requests ; extra == 'lint'
Provides-Extra: test
Requires-Dist: pytest ; extra == 'test'
Requires-Dist: pytest-click ; extra == 'test'
Requires-Dist: pytest-cov ; extra == 'test'
Requires-Dist: pytest-custom-exit-code ; extra == 'test'
Requires-Dist: pytest-mock ; extra == 'test'
